arm_float_detector/__init__.py
arm_float_detector/arm_float_detector.py
arm_float_detector-0.3.0.dist-info/METADATA
arm_float_detector-0.3.0.dist-info/WHEEL
arm_float_detector-0.3.0.dist-info/entry_points.txt
arm_float_detector-0.3.0.dist-info/top_level.txt
arm_float_detector-0.3.0.dist-info/RECORD
