Metadata-Version: 2.1
Name: arm-float-detector
Version: 0.3.0
Summary: Detect software floating point usage in arm binaries
Home-page: https://github.com/noahp/arm-float-detector
Author: Noah Pendleton
Author-email: 2538614+noahp@users.noreply.github.com
License: MIT
Project-URL: Code, https://github.com/noahp/arm-float-detector
Project-URL: Issue tracker, https://github.com/noahp/arm-float-detector/issues
Platform: UNKNOWN
Classifier: License :: OSI Approved :: MIT License
Classifier: Programming Language :: Python :: 2.7
Classifier: Programming Language :: Python :: 3.6
Classifier: Programming Language :: Python :: 3.7
Classifier: Programming Language :: Python :: 3.8
Classifier: Operating System :: OS Independent
